tapps_agents/__init__.py
tapps_agents/agents/__init__.py
tapps_agents/agents/analyst/SKILL.md
tapps_agents/agents/analyst/__init__.py
tapps_agents/agents/analyst/agent.py
tapps_agents/agents/architect/SKILL.md
tapps_agents/agents/architect/__init__.py
tapps_agents/agents/architect/agent.py
tapps_agents/agents/architect/pattern_detector.py
tapps_agents/agents/debugger/SKILL.md
tapps_agents/agents/debugger/__init__.py
tapps_agents/agents/debugger/agent.py
tapps_agents/agents/debugger/error_analyzer.py
tapps_agents/agents/designer/SKILL.md
tapps_agents/agents/designer/__init__.py
tapps_agents/agents/designer/agent.py
tapps_agents/agents/designer/visual_designer.py
tapps_agents/agents/documenter/SKILL.md
tapps_agents/agents/documenter/__init__.py
tapps_agents/agents/documenter/agent.py
tapps_agents/agents/documenter/doc_generator.py
tapps_agents/agents/documenter/doc_validator.py
tapps_agents/agents/documenter/framework_doc_updater.py
tapps_agents/agents/enhancer/SKILL.md
tapps_agents/agents/enhancer/__init__.py
tapps_agents/agents/enhancer/agent.py
tapps_agents/agents/evaluator/__init__.py
tapps_agents/agents/evaluator/agent.py
tapps_agents/agents/evaluator/priority_evaluator.py
tapps_agents/agents/evaluator/quality_analyzer.py
tapps_agents/agents/evaluator/report_generator.py
tapps_agents/agents/evaluator/usage_analyzer.py
tapps_agents/agents/evaluator/workflow_analyzer.py
tapps_agents/agents/implementer/SKILL.md
tapps_agents/agents/implementer/__init__.py
tapps_agents/agents/implementer/agent.py
tapps_agents/agents/implementer/auto_fix.py
tapps_agents/agents/implementer/code_generator.py
tapps_agents/agents/improver/SKILL.md
tapps_agents/agents/improver/__init__.py
tapps_agents/agents/improver/agent.py
tapps_agents/agents/ops/SKILL.md
tapps_agents/agents/ops/__init__.py
tapps_agents/agents/ops/agent.py
tapps_agents/agents/ops/dependency_analyzer.py
tapps_agents/agents/orchestrator/SKILL.md
tapps_agents/agents/orchestrator/__init__.py
tapps_agents-3.5.33.dist-info/licenses/LICENSE
tapps_agents-3.5.33.dist-info/METADATA
tapps_agents-3.5.33.dist-info/WHEEL
tapps_agents-3.5.33.dist-info/entry_points.txt
tapps_agents-3.5.33.dist-info/top_level.txt
tapps_agents-3.5.33.dist-info/RECORD
