Metadata-Version: 2.4
Name: tapps-agents
Version: 3.5.33
Summary: A specification framework for defining, configuring, and orchestrating coding agents
Author: Tapps
Maintainer: Tapps
License: MIT
Project-URL: Homepage, https://github.com/wtthornton/TappsCodingAgents
Project-URL: Repository, https://github.com/wtthornton/TappsCodingAgents
Project-URL: Documentation, https://github.com/wtthornton/TappsCodingAgents
Project-URL: Issues, https://github.com/wtthornton/TappsCodingAgents/issues
Keywords: ai,agents,coding,workflow,automation
Classifier: Development Status :: 4 - Beta
Classifier: Intended Audience :: Developers
Classifier: License :: OSI Approved :: MIT License
Classifier: Programming Language :: Python :: 3
Classifier: Programming Language :: Python :: 3.12
Classifier: Programming Language :: Python :: 3.13
Requires-Python: >=3.12
License-File: LICENSE
Requires-Dist: pydantic>=2.12.5
Requires-Dist: httpx>=0.28.1
Requires-Dist: pyyaml>=6.0.3
Requires-Dist: aiohttp>=3.13.3
Requires-Dist: psutil>=7.2.1
Requires-Dist: radon>=6.0.1
Requires-Dist: bandit>=1.9.2
Requires-Dist: coverage>=7.13.1
Requires-Dist: jinja2>=3.1.6
Requires-Dist: plotly>=6.5.2
Requires-Dist: packaging<27,>=23.2
Requires-Dist: rich>=14.2.0
Requires-Dist: aiofiles>=25.1.0
Provides-Extra: dev
Requires-Dist: black>=26.1.0; extra == "dev"
Requires-Dist: ruff<1.0,>=0.14.13; extra == "dev"
Requires-Dist: mypy<2.0,>=1.19.1; extra == "dev"
Requires-Dist: types-PyYAML>=6.0.12.20250915; extra == "dev"
Requires-Dist: pytest>=9.0.2; extra == "dev"
Requires-Dist: pytest-asyncio>=1.3.0; extra == "dev"
Requires-Dist: pytest-cov>=7.0.0; extra == "dev"
Requires-Dist: pytest-mock>=3.15.1; extra == "dev"
Requires-Dist: pytest-timeout>=2.4.0; extra == "dev"
Requires-Dist: pytest-xdist>=3.8.0; extra == "dev"
Requires-Dist: pytest-sugar>=1.1.1; extra == "dev"
Requires-Dist: pytest-html>=4.1.1; extra == "dev"
Requires-Dist: pytest-rich>=0.2.0; extra == "dev"
Requires-Dist: pylint>=4.0.4; extra == "dev"
Requires-Dist: pip-audit>=2.10.0; extra == "dev"
Requires-Dist: pip-tools>=7.5.2; extra == "dev"
Provides-Extra: dependency-analysis
Requires-Dist: pipdeptree>=2.30.0; extra == "dependency-analysis"
Dynamic: license-file
